README.md
setup.py
upload_on_pip
.eggs/webencodings-0.5.1-py3.7.egg/EGG-INFO/DESCRIPTION.rst
.eggs/webencodings-0.5.1-py3.7.egg/EGG-INFO/PKG-INFO
.eggs/webencodings-0.5.1-py3.7.egg/EGG-INFO/RECORD
.eggs/webencodings-0.5.1-py3.7.egg/EGG-INFO/WHEEL
.eggs/webencodings-0.5.1-py3.7.egg/EGG-INFO/metadata.json
.eggs/webencodings-0.5.1-py3.7.egg/webencodings/__init__.py
.eggs/webencodings-0.5.1-py3.7.egg/webencodings/labels.py
.eggs/webencodings-0.5.1-py3.7.egg/webencodings/mklabels.py
.eggs/webencodings-0.5.1-py3.7.egg/webencodings/tests.py
.eggs/webencodings-0.5.1-py3.7.egg/webencodings/x_user_defined.py
womg/LICENSE
womg/__init__.py
womg/__main__.py
womg.egg-info/PKG-INFO
womg.egg-info/SOURCES.txt
womg.egg-info/dependency_links.txt
womg.egg-info/entry_points.txt
womg.egg-info/requires.txt
womg.egg-info/top_level.txt
womg/n2i/__init__.py
womg/n2i/__main__.py
womg/n2i/graph.py
womg/n2i/node2vec.py
womg/n2i/tfoptimizer.py
womg/node2vec_git/LICENSE.md
womg/node2vec_git/README.md
womg/node2vec_git/__init__.py
womg/node2vec_git/emb/karate.emb
womg/node2vec_git/emb/lesmiserables.emb
womg/node2vec_git/node2vec_spark/README.md
womg/node2vec_git/node2vec_spark/src/main/resources/log4j2.properties
womg/node2vec_git/node2vec_spark/src/main/scala/com/navercorp/Main.scala
womg/node2vec_git/node2vec_spark/src/main/scala/com/navercorp/Node2vec.scala
womg/node2vec_git/node2vec_spark/src/main/scala/com/navercorp/Word2vec.scala
womg/node2vec_git/node2vec_spark/src/main/scala/com/navercorp/graph/GraphOps.scala
womg/node2vec_git/node2vec_spark/src/main/scala/com/navercorp/graph/package.scala
womg/node2vec_git/node2vec_spark/src/main/scala/com/navercorp/lib/AbstractParams.scala
womg/node2vec_git/src/node2vec_class.py
womg/node2vec_git/src/node2vec_main.py
womg/topic/__init__.py
womg/topic/lda_extended.py
womgdata/docs/demo_corpus/AP880212-0078.txt
womgdata/docs/demo_corpus/AP880213-0055.txt
womgdata/docs/training_corpus/w_acad_1990.txt
womgdata/docs/training_corpus/w_acad_1991.txt
womgdata/docs/training_corpus/w_acad_1992.txt
womgdata/docs/training_corpus/w_acad_1993.txt
womgdata/docs/training_corpus/w_acad_1994.txt
womgdata/docs/training_corpus/w_acad_1995.txt
womgdata/docs/training_corpus/w_acad_1996.txt
womgdata/docs/training_corpus/w_acad_1997.txt
womgdata/docs/training_corpus/w_acad_1998.txt
womgdata/docs/training_corpus/w_acad_1999.txt
womgdata/docs/training_corpus/w_acad_2000.txt
